MANIFEST.in
README.rst
setup.py
keras_bed_sequence/__init__.py
keras_bed_sequence/__version__.py
keras_bed_sequence/bed_sequence.py
keras_bed_sequence.egg-info/PKG-INFO
keras_bed_sequence.egg-info/SOURCES.txt
keras_bed_sequence.egg-info/dependency_links.txt
keras_bed_sequence.egg-info/requires.txt
keras_bed_sequence.egg-info/top_level.txt
keras_bed_sequence/utils/__init__.py
keras_bed_sequence/utils/fast_to_categorical.py
keras_bed_sequence/utils/nucleotides_to_numbers.py