Metadata-Version: 2.1
Name: keras-bed-sequence
Version: 1.1.6
Summary: Lazily one-hot encoding bed sequences using Keras Sequence.
Home-page: https://github.com/LucaCappelletti94/keras_bed_sequence
Author: Luca Cappelletti
Author-email: cappelletti.luca94@gmail.com
License: MIT
Platform: UNKNOWN
Classifier: Development Status :: 3 - Alpha
Classifier: License :: OSI Approved :: MIT License
Classifier: Programming Language :: Python :: 3
Requires-Python: >3.5.2
Provides-Extra: test
